{"cameraMode":{"drawMode":0,"name":"Shaded","section":"Shading Mode"},"sceneLighting":true,"audioPlay":false,"sceneViewState":{"m_AlwaysRefresh":false,"showFog":true,"showSkybox":true,"showFlares":true,"showImageEffects":true,"showParticleSystems":true,"showVisualEffectGraphs":true,"m_FxEnabled":true},"in2DMode":false,"pivot":{"x":-21.11019515991211,"y":2.4395649433135988,"z":-14.362336158752442},"rotation":{"x":0.194740429520607,"y":0.348952054977417,"z":-0.07439929246902466,"w":0.913710355758667},"size":11.626321792602539,"orthographic":false}